dingtalk_robot
