Metadata-Version: 1.1
Name: dingtalk-robot
Version: 0.0.3
Summary: Python Package for Dingtalk Robot
Home-page: https://github.com/SF-Zhou/DingtalkRobot
Author: SF-Zhou
Author-email: sfzhou.scut@gmail.com
License: MIT
Keywords: tools dingtalk robot
Platform: UNKNOWN
Classifier: Development Status :: 3 - Alpha
Classifier: Intended Audience :: Developers
Classifier: License :: OSI Approved :: MIT License
Classifier: Programming Language :: Python :: 3
